openai_forward/__init__.py
openai_forward/__main__.py
openai_forward/app.py
openai_forward/config.py
openai_forward/helper.py
openai_forward/content/__init__.py
openai_forward/content/chat.py
openai_forward/content/decode.py
openai_forward/content/whisper.py
openai_forward/forwarding/__init__.py
openai_forward/forwarding/base.py
openai_forward/forwarding/extra.py
openai_forward/forwarding/openai.py
openai_forward/forwarding/settings.py
llm_forward-0.0.1a0.dist-info/METADATA
llm_forward-0.0.1a0.dist-info/WHEEL
llm_forward-0.0.1a0.dist-info/entry_points.txt
llm_forward-0.0.1a0.dist-info/licenses/LICENSE
llm_forward-0.0.1a0.dist-info/RECORD
