Metadata-Version: 2.1
Name: llm_forward
Version: 0.0.1a0
Summary: 🚀 OpenAI API Reverse Proxy · ChatGPT API Proxy
Project-URL: Homepage, https://github.com/beidongjiedeguang/openai-forward
Project-URL: Documentation, https://github.com/beidongjiedeguang/openai-forward#openai-forward
Project-URL: Issues, https://github.com/beidongjiedeguang/openai-forward/issues
Project-URL: Source, https://github.com/beidongjiedeguang/openai-forward
Author-email: kunyuan <beidongjiedeguang@gmail.com>
License-Expression: MIT
License-File: LICENSE
Keywords: OpenAI API Forwarding,chatgpt,fastapi,openai,openai-api,openai-proxy,python,streaming-api
Classifier: Development Status :: 5 - Production/Stable
Classifier: Operating System :: OS Independent
Classifier: Programming Language :: Python :: 3
Requires-Python: >=3.6
Requires-Dist: fastapi>=0.90.0
Requires-Dist: fire
Requires-Dist: httpx>=0.24
Requires-Dist: loguru>=0.7.0
Requires-Dist: orjson>=3.9
Requires-Dist: python-dotenv
Requires-Dist: pytz
Requires-Dist: rich
Requires-Dist: slowapi==0.1.8
Requires-Dist: uvicorn>=0.21.0
Provides-Extra: dev
Requires-Dist: openai>=0.27.8; extra == 'dev'
Requires-Dist: schedule; extra == 'dev'
Requires-Dist: sparrow-python; extra == 'dev'
Provides-Extra: test
Requires-Dist: openai>=0.27.8; extra == 'test'
Requires-Dist: pytest; extra == 'test'
Requires-Dist: sparrow-python; extra == 'test'
